README
setup.py
cphhpc/__init__.py
cphhpc/device/__init__.py
cphhpc/device/gpu/__init__.py
cphhpc/device/gpu/opencl.py
cphhpc/image/__init__.py
cphhpc/image/filter/__init__.py
cphhpc/image/filter/gauss2d.py
cphhpc/image/filter/medfilt2d.py
cphhpc/image/filter/sobel.py
cphhpc/signal/__init__.py
cphhpc/signal/convolution/__init__.py
cphhpc/signal/convolution/kernel.py
cphhpctoolbox.egg-info/PKG-INFO
cphhpctoolbox.egg-info/SOURCES.txt
cphhpctoolbox.egg-info/dependency_links.txt
cphhpctoolbox.egg-info/requires.txt
cphhpctoolbox.egg-info/top_level.txt