Metadata-Version: 1.1
Name: cphhpctoolbox
Version: 0.0.1
Summary: CPHHPC Toolbox is a set of high performance Python extensions
Home-page: ('http://code.google.com/p/cphhpc/',)
Author: The CPHHPC Toolbox maintainers
Author-email: martin DOT rehr AT gmail DOT com
License: ('GNU GPL v2',)
Download-URL: ('http://code.google.com/p/cphhpc/downloads/list',)
Keywords: python,numpy,science,research,cpu,gpu
Platform: All
Classifier: Development Status :: 3 - Alpha
Classifier: Environment :: Console
Classifier: Intended Audience :: Developers
Classifier: Intended Audience :: Science/Research
Classifier: License :: OSI Approved :: GNU General Public License (GPL)
Classifier: Operating System :: OS Independent
Classifier: Programming Language :: Python
Requires: numpy
Requires: pyopencl
